Metadata-Version: 2.1
Name: weilaizz
Version: 2.1.7
Summary: webUI.
Home-page: https://gitee.com/weilai112/web-ui_auto.git
Author: Wei Lai
Author-email: 14922227@qq.com
License: MIT
Platform: UNKNOWN
Classifier: License :: OSI Approved :: MIT License
Classifier: Programming Language :: Python
Classifier: Programming Language :: Python :: 3
Classifier: Programming Language :: Python :: 3.6
Classifier: Programming Language :: Python :: Implementation :: CPython
Classifier: Programming Language :: Python :: Implementation :: PyPy
Requires-Python: >=3.6.0
License-File: LICENSE
